nonebot_plugin_pixivbot_telegram/__init__.py
nonebot_plugin_pixivbot_telegram/config.py
nonebot_plugin_pixivbot_telegram/protocol_dep/__init__.py
nonebot_plugin_pixivbot_telegram/protocol_dep/authenticator.py
nonebot_plugin_pixivbot_telegram/protocol_dep/post_dest.py
nonebot_plugin_pixivbot_telegram/protocol_dep/postman.py
nonebot_plugin_pixivbot_telegram-1.5.0.post1.dist-info/LICENSE
nonebot_plugin_pixivbot_telegram-1.5.0.post1.dist-info/WHEEL
nonebot_plugin_pixivbot_telegram-1.5.0.post1.dist-info/METADATA
nonebot_plugin_pixivbot_telegram-1.5.0.post1.dist-info/RECORD
