Metadata-Version: 2.1
Name: nonebot-plugin-pixivbot-telegram
Version: 1.5.0.post1
Summary: Nonebot Plugin Pixivbot (Telegram)
Home-page: https://github.com/ssttkkl/nonebot-plugin-pixivbot-telegram
License: MIT
Author: ssttkkl
Author-email: huang.wen.long@hotmail.com
Requires-Python: >=3.9,<4.0
Classifier: License :: OSI Approved :: MIT License
Classifier: Programming Language :: Python :: 3
Classifier: Programming Language :: Python :: 3.9
Classifier: Programming Language :: Python :: 3.10
Classifier: Programming Language :: Python :: 3.11
Requires-Dist: asyncache (>=0.1.1,<0.4.0)
Requires-Dist: cachetools (>=5.2.0,<6.0.0)
Requires-Dist: nonebot-adapter-telegram (>=0.1.0b3,<0.2.0)
Requires-Dist: nonebot2 (>=2.0.0rc1,<3.0.0)
Project-URL: Repository, https://github.com/ssttkkl/nonebot-plugin-pixivbot-telegram
